Scripts/__init__.py
Scripts/confluence.py
Scripts/empty_creds.py
Scripts/fix_report_hyperlinks.py
Scripts/jira_issues.py
Scripts/tooltip.py
Scripts/Model/__init__.py
Scripts/Model/asset_form.py
Scripts/Model/model2csv.py
Scripts/Model/set_assets.py
Scripts/Model/set_metadata_tags.py
Scripts/Model/tmt2td.py
Scripts/Scoring/__init__.py
Scripts/Scoring/cvss.py
Scripts/Scoring/owasp_rr.py
Scripts/Template/__init__.py
Scripts/Template/template2sql.py
Scripts/Template/template2xlsx.py
Scripts/Template/template_diff.py
Scripts/Template/xlsx2template.py
TMTool-0.0.50.dist-info/LICENSE
TMTool-0.0.50.dist-info/METADATA
TMTool-0.0.50.dist-info/WHEEL
TMTool-0.0.50.dist-info/entry_points.txt
TMTool-0.0.50.dist-info/top_level.txt
TMTool-0.0.50.dist-info/RECORD
