Metadata-Version: 2.1
Name: TMTool
Version: 0.0.50
Summary: python tool for Microsoft Threat modeling tool
Author-email: Tyler Martin <tmart234@gmail.com>
Maintainer-email: Tyler Martin <tmart234@gmail.com>
License: MIT
Project-URL: homepage, https://github.com/tmart234/TMT
Project-URL: documentation, https://github.com/tmart234/TMT
Project-URL: repository, https://github.com/tmart234/TMT
Requires-Python: >=3.7
License-File: LICENSE
Requires-Dist: tkinter
Requires-Dist: openpyxl
Requires-Dist: xlsxwriter
Requires-Dist: Click
Requires-Dist: lxml
Requires-Dist: atlassian-python-api
Requires-Dist: pypandoc
Requires-Dist: xmltodict
Requires-Dist: jira
Requires-Dist: ttkthemes
Requires-Dist: enum37 ; python_version < "3.7"
